{
	"id": 94042166,
	"body": "The basic example crashes with the log below.\r\n\r\n```\r\n/ActivityManager(  849): Process com.example.basic (pid 16799) has died\r\nI/ActivityManager(  849): Start proc com.example.basic for activity com.example.basic/android.app.NativeActivity: pid=16819 uid=10082 gids={50082, 9997} abi=armeabi\r\nW/linker  (16819): libbasic.so has text relocations. This is wasting memory and prevents security hardening. Please fix.\r\nF/libc    (16819): Fatal signal 11 (SIGSEGV), code 2, fault addr 0x7af3c000 in tid 16835 (Thread-1536)\r\nI/libc    (16819): Suppressing debuggerd output because prctl(PR_GET_DUMPABLE)==0\r\nI/Zygote  (  609): Process 16819 exited due to signal (11)\r\nI/ActivityManager(  849): Process com.example.basic (pid 16819) has died\r\nI/ActivityManager(  849): Start proc com.example.basic for activity com.example.basic/android.app.NativeActivity: pid=16836 uid=10082 gids={50082, 9997} abi=armeabi\r\nW/linker  (16836): libbasic.so has text relocations. This is wasting memory and prevents security hardening. Please fix.\r\nE/Go      (16836): fatal error: malloc deadlock\r\nF/libc    (16836): Fatal signal 11 (SIGSEGV), code 2, fault addr 0x7af3c000 in tid 16852 (Thread-1541)\r\nI/libc    (16836): Suppressing debuggerd output because prctl(PR_GET_DUMPABLE)==0\r\nI/Zygote  (  609): Process 16836 exited due to signal (11)\r\nI/ActivityManager(  849): Process com.example.basic (pid 16836) has died\r\nW/ActivityManager(  849): Force removing ActivityRecord{3f5c1604 u0 com.example.basic/android.app.NativeActivity t231}: app died, no saved state\r\n```\r\n",
	"user": {
		"login": "rakyll",
		"id": 108380,
		"type": "User",
		"site_admin": false
	},
	"created_at": "2015-04-17T18:10:09Z",
	"updated_at": "2015-04-17T18:10:09Z"
}
