{
	"id": 66065297,
	"body": "\u003ca id=\"c6\"\u003e\u003c/a\u003eComment 6:\n\n\u003cpre\u003eYes, \"DEF_FUNCTION_TYPE (VOID, PLONGLONG, LONGLONG)\"  is in\n/home/tjyang/gccgo-src/gcc/config/i386/i386-builtin-types.def at correct position.\n\u0026lt;snipped\u0026gt;\nDEF_FUNCTION_TYPE (VOID, PFLOAT, V4SF)\nDEF_FUNCTION_TYPE (VOID, PFLOAT, V8SF)\nDEF_FUNCTION_TYPE (VOID, PINT, INT)\nDEF_FUNCTION_TYPE (VOID, PLONGLONG, LONGLONG)\nDEF_FUNCTION_TYPE (VOID, PULONGLONG, ULONGLONG)\nDEF_FUNCTION_TYPE (VOID, PV2SI, V2SI)\nDEF_FUNCTION_TYPE (VOID, PV2DI, V2DI)\nDEF_FUNCTION_TYPE (VOID, PV2SF, V4SF)\nDEF_FUNCTION_TYPE (VOID, PV4DI, V4DI)\nDEF_FUNCTION_TYPE (VOID, PV4SF, V4SF)\nDEF_FUNCTION_TYPE (VOID, PV8SF, V8SF)\nDEF_FUNCTION_TYPE (VOID, UNSIGNED, UNSIGNED)\n\u0026lt;snipped\u0026gt;\u003c/pre\u003e",
	"user": {
		"login": "tjyang",
		"id": 378638,
		"type": "User",
		"site_admin": false
	},
	"created_at": "2012-03-23T11:49:19Z",
	"updated_at": "2014-12-22T06:12:30Z"
}
