{
	"id": 140244103,
	"body": "@jdmontenegro thank you for your reply. These crashes are commonly caused by races in your program. Have you run your tests or built a race enable version of your program ?\r\n\r\nTo run your tests with the race detector\r\n```\r\ngo test -race github.com/you/yourpackage/...\r\n```\r\nTo build a race enable version of your program\r\n```\r\ngo build -race github.com/you/yourpackage/yourcommand\r\n```",
	"user": {
		"login": "davecheney",
		"id": 7171,
		"type": "User",
		"site_admin": false
	},
	"created_at": "2015-09-15T00:59:34Z",
	"updated_at": "2015-09-15T00:59:34Z"
}
