{
	"id": 66083890,
	"body": "\u003ca id=\"c14\"\u003e\u003c/a\u003eComment 14:\n\n\u003cpre\u003eDoes clang implicitly read from some kind of .clangrc file or something\nlike that? There is clearly something different between your system and\nmine other than the Xcode and clang versions.\n\nI am trying Xcode 5 now...\u003c/pre\u003e",
	"user": {
		"login": "rsc",
		"id": 104030,
		"type": "User",
		"site_admin": false
	},
	"created_at": "2013-10-09T14:58:58Z",
	"updated_at": "2014-12-08T10:33:42Z"
}
