{
	"id": 51288286,
	"number": 8495,
	"state": "closed",
	"title": "runtime: handle page sizes other than 4096 properly",
	"body": "\u003cpre\u003eThis is a placeholder issue to ensure that platforms that don't use 4096 page sizes are\nproperly handled.\n\nThe specific use case is ppc64 which can have page sizes other than 4k, see\n\u003ca href=\"https://code.google.com/p/gofrontend/source/detail?r=986b937904fd9768c40948ece0bc233b441abb98\"\u003ehttps://code.google.com/p/gofrontend/source/detail?r=986b937904fd9768c40948ece0bc233b441abb98\u003c/a\u003e\u003c/pre\u003e",
	"user": {
		"login": "davecheney",
		"id": 7171,
		"type": "User",
		"site_admin": false
	},
	"labels": [
		{
			"name": "FrozenDueToAge"
		}
	],
	"comments": 3,
	"closed_at": "2014-12-08T10:47:13Z",
	"created_at": "2014-08-08T00:28:34Z",
	"updated_at": "2016-06-25T01:39:17Z",
	"milestone": {
		"id": 1067218,
		"number": 21,
		"title": "Go1.4"
	}
}
