{
	"id": 250353299,
	"body": "\u003e @aclements Is this bug still relevant with the new changes to reduce the amount of extra work that is done for each assist?\r\n\r\nYes. This issue arises because there's no work *at all* for assists at the beginning of the cycle, not because they want more work than they can get. Reducing the extra work does mean assists become useful earlier in the cycle, just not yet at the beginning.",
	"user": {
		"login": "aclements",
		"id": 2688315,
		"type": "User",
		"site_admin": false
	},
	"created_at": "2016-09-29T02:16:13Z",
	"updated_at": "2016-09-29T02:16:13Z"
}
