{
	"id": 66063778,
	"body": "\u003ca id=\"c9\"\u003e\u003c/a\u003eComment 9:\n\n\u003cpre\u003e$go list -json github.com/ajstarks/svgo\n{\n\t\"Dir\": \"/home/dlin/go/src/github.com/ajstarks/svgo\",\n\t\"ImportPath\": \"github.com/ajstarks/svgo\",\n\t\"Name\": \"svg\",\n\t\"Doc\": \"Package svg provides an API for generating Scalable Vector Graphics (SVG)\",\n\t\"Target\": \"/home/dlin/go/pkg/linux_amd64/github.com/ajstarks/svgo.a\",\n\t\"Stale\": true,\n\t\"Root\": \"/home/dlin/go\",\n\t\"GoFiles\": [\n\t\t\"svg.go\"\n\t],\n\t\"Imports\": [\n\t\t\"encoding/xml\",\n\t\t\"fmt\",\n\t\t\"io\",\n\t\t\"strings\"\n\t],\n\t\"Deps\": [\n\t\t\"bufio\",\n\t\t\"bytes\",\n\t\t\"encoding/xml\",\n\t\t\"errors\",\n\t\t\"fmt\",\n\t\t\"io\",\n\t\t\"math\",\n\t\t\"os\",\n\t\t\"reflect\",\n\t\t\"runtime\",\n\t\t\"strconv\",\n\t\t\"strings\",\n\t\t\"sync\",\n\t\t\"sync/atomic\",\n\t\t\"syscall\",\n\t\t\"time\",\n\t\t\"unicode\",\n\t\t\"unicode/utf8\",\n\t\t\"unsafe\"\n\t]\n}\u003c/pre\u003e",
	"user": {
		"login": "dlintw",
		"id": 326179,
		"type": "User",
		"site_admin": false
	},
	"created_at": "2012-03-03T00:35:48Z",
	"updated_at": "2014-12-08T10:16:22Z"
}
