{
	"id": 66078450,
	"body": "\u003ca id=\"c30\"\u003e\u003c/a\u003eComment 30 by **hb@hannobraun.de**:\n\n\u003cpre\u003eRe #29, no problem, just let me know where to send it (I only see a shortened version of\nyour email address).\n\nThe bt output (see report above for more gdb output):\n\n(gdb) bt\n#0  runtime.gentraceback (pc0=void, sp=void, gp=void, skip=void, pcbuf=void, max=void,\nfn=void, arg=void)\n    at /usr/lib/go/src/pkg/runtime/traceback_x86.c:88\n#1  0x000000000041c743 in runtime.sigprof (pc=void, sp=void, lr=void, gp=void) at\n/usr/lib/go/src/pkg/runtime/proc.c:1790\n#2  0x000000000041e931 in runtime.sighandler (sig=void, info=void, ctxt=void, gp=void)\nat /usr/lib/go/src/pkg/runtime/signal_amd64.c:51\n#3  0x0000000000428144 in runtime.sigtramp () at\n/usr/lib/go/src/pkg/runtime/sys_linux_amd64.s:207\n#4  0x0000000000428160 in ?? () at /usr/lib/go/src/pkg/runtime/sys_linux_amd64.s:213\n#5  0x0000000000000000 in ?? ()\u003c/pre\u003e",
	"user": {
		"login": "gopherbot",
		"id": 8566911,
		"type": "User",
		"site_admin": false
	},
	"created_at": "2013-05-03T12:16:25Z",
	"updated_at": "2014-12-08T10:28:50Z"
}
