{
	"id": 236395772,
	"body": "\u003e why not also bump the 500 to 501, per https://msdn.microsoft.com/en-us/library/windows/desktop/aa370556(v=vs.85).aspx ?\r\n\r\nI am just trying to change as little as possible. So we don't break some users. I know nothing about MSIs.\r\n\r\n\u003e If a user really wants to try it on an earlier Windows, they can use the ZIP file instead of the MSI.\r\n\r\nSure. They can use MSI or ZIP file.\r\n\r\nAlex",
	"user": {
		"login": "alexbrainman",
		"id": 9796621,
		"type": "User",
		"site_admin": false
	},
	"created_at": "2016-07-30T23:25:29Z",
	"updated_at": "2016-07-30T23:25:29Z"
}
