{
	"id": 206673098,
	"body": "I think this is terrible and is fixing the wrong problem. This would mean that if etcd vendors context and exposes an vendored context in their API, two parties (let's call them A and B) could implement that interface by referring to the long ugly `path/to/pkg/vendor/context` but A and B would be unable to use that same implementation to implement interfaces taking a different context package, or even the real context package.\r\n\r\nI think this would make the situation worse.\r\n",
	"user": {
		"login": "bradfitz",
		"id": 2621,
		"type": "User",
		"site_admin": false
	},
	"reactions": {
		"total_count": 7,
		"+1": 7
	},
	"created_at": "2016-04-07T03:01:08Z",
	"updated_at": "2016-04-07T03:01:08Z"
}
