{
	"id": 66070245,
	"body": "\u003ca id=\"c4\"\u003e\u003c/a\u003eComment 4:\n\n\u003cpre\u003eThe testing flags are documented at\n\u003ca href=\"http://golang.org/cmd/go/#Description_of_testing_flags\"\u003ehttp://golang.org/cmd/go/#Description_of_testing_flags\u003c/a\u003e and 'go help\ntestflag'. Perhaps a link to those is all that is needed in package\ntesting itself.\n\nRuss\u003c/pre\u003e",
	"user": {
		"login": "rsc",
		"id": 104030,
		"type": "User",
		"site_admin": false
	},
	"created_at": "2012-09-14T15:14:01Z",
	"updated_at": "2014-12-08T10:21:42Z"
}
