{
	"id": 66060854,
	"body": "\u003ca id=\"c4\"\u003e\u003c/a\u003eComment 4:\n\n\u003cpre\u003eCould we have the option, at least for \"go installl\", to toggle the\nbuilding/installation of standard library packages? \n\nThe current iteration works well if I am on a privileged account or if I have write\naccess to both $GOROOT and $GOPATH, but If I have no write access to $GOROOT/pkg then\ninstalling packages fails.\n\n    ±! ganderson@excession [18:41:39] ../goconfig/config (master)                                                                                                                                 \n    : echo $GOROOT \u0026\u0026 echo $GOPATH                                                                                                                                                                \n    /usr/lib64/go                                                                                                                                                                                 \n    /home/ganderson/go                                                                                                                                                                            \n    ±! ganderson@excession [18:41:58] ../goconfig/config (master)                                                                                                                                 \n    : go install                                                                                                                                                                                  \n    open /usr/lib64/go/pkg/linux_amd64/sync/atomic.a: permission denied                                                                                                                           \n    open /usr/lib64/go/pkg/linux_amd64/unicode.a: permission denied                                                                                                                               \n    open /usr/lib64/go/pkg/linux_amd64/sort.a: permission denied\n\nI had envisioned perhaps something like the following:\n\n    The -s flag ommits installing packages from the standard library, if both -a and -s are passed, \n    the -a option supersedes the -s option.\n\nOr perhaps no flag at all but allow the operation to continue and write the user package\ninto $GOPATH.\u003c/pre\u003e",
	"user": {
		"login": "gnanderson",
		"id": 38514,
		"type": "User",
		"site_admin": false
	},
	"created_at": "2011-12-24T17:50:39Z",
	"updated_at": "2014-12-08T10:13:51Z"
}
