{
	"id": 66067130,
	"body": "\u003ca id=\"c3\"\u003e\u003c/a\u003eComment 3:\n\n\u003cpre\u003eMy guess is that you passed a struct (not a struct pointer) to\nencoding/json and that the string was one of the fields in the struct.\nIt would be good to test this theory and if so make Unmarshal give a\nbetter error.\n\nI will do this if no one else beats me to it, but probably not soon.\u003c/pre\u003e\n\n_Labels changed: added **go1.0.2**._",
	"user": {
		"login": "rsc",
		"id": 104030,
		"type": "User",
		"site_admin": false
	},
	"created_at": "2012-05-15T17:42:42Z",
	"updated_at": "2014-12-08T10:19:05Z"
}
