{
	"id": 51284413,
	"number": 5937,
	"state": "closed",
	"title": "doc: math/rand should mention Seed(seed int64) in the overview",
	"body": "by **brian@crashlytics.com**:\n\n\u003cpre\u003eI was very surprised to learn that my calls to rand.Intn(15) were returning the same\nsequence of numbers each time. Fortunately, the fine folks in IRC were able to point out\nwhat I had not noticed, but since the intent of math/rand is different than crypto/rand,\nI think people stumbling upon it would benefit from some basic guidance about the PRNG's\nbehavior in the overview.\u003c/pre\u003e",
	"user": {
		"login": "gopherbot",
		"id": 8566911,
		"type": "User",
		"site_admin": false
	},
	"labels": [
		{
			"name": "FrozenDueToAge"
		}
	],
	"assignee": {
		"login": "adg",
		"id": 8446613,
		"type": "User",
		"site_admin": false
	},
	"comments": 4,
	"closed_at": "2014-12-08T10:32:37Z",
	"created_at": "2013-07-23T02:31:40Z",
	"updated_at": "2016-06-24T22:52:28Z"
}
