{
	"id": 130567284,
	"number": 14188,
	"state": "closed",
	"title": "net/http: further restrict which trailers may be sent",
	"body": "http://tools.ietf.org/html/rfc7230#section-4.1.2\r\n```\r\n   A sender MUST NOT generate a trailer that contains a field necessary\r\n   for message framing (e.g., Transfer-Encoding and Content-Length),\r\n   routing (e.g., Host), request modifiers (e.g., controls and\r\n   conditionals in Section 5 of [RFC7231]), authentication (e.g., see\r\n   [RFC7235] and [RFC6265]), response control data (e.g., see Section\r\n   7.1 of [RFC7231]), or determining how to process the payload (e.g.,\r\n   Content-Encoding, Content-Type, Content-Range, and Trailer).\r\n```",
	"user": {
		"login": "bradfitz",
		"id": 2621,
		"type": "User",
		"site_admin": false
	},
	"assignee": {
		"login": "bradfitz",
		"id": 2621,
		"type": "User",
		"site_admin": false
	},
	"comments": 1,
	"closed_at": "2016-05-19T03:54:02Z",
	"created_at": "2016-02-02T04:04:29Z",
	"updated_at": "2016-05-19T03:54:02Z",
	"milestone": {
		"id": 1414133,
		"number": 31,
		"title": "Go1.7"
	}
}
