{
	"id": 150633938,
	"body": "@cznic The result is \"perfectly logical\" but is not great from a readability point of view as mentioned before.\r\n```\r\na + b * *p\r\n```\r\ndoes seem clearer than\r\n```\r\na + b**p\r\n```\r\n(a**b means a to the power of b in some languages, and we even use that notation in some comments to mean that).",
	"user": {
		"login": "griesemer",
		"id": 8528975,
		"type": "User",
		"site_admin": false
	},
	"created_at": "2015-10-23T17:01:09Z",
	"updated_at": "2015-10-23T17:01:09Z"
}
