{
	"id": 206464300,
	"body": "Yes, you can, or just implement readSlice yourself in like 5 lines. It is just a matter of convenience and bufio already has it (in fact, it took me a while to figure out why do I remember that I could use ReadSlice - I've used it on bufio.Reader previously), so I thought I'd mention it and/or send a patch.",
	"user": {
		"login": "Tasssadar",
		"id": 120108,
		"type": "User",
		"site_admin": false
	},
	"created_at": "2016-04-06T16:59:16Z",
	"updated_at": "2016-04-06T16:59:16Z"
}
