{
	"id": 144202270,
	"body": "In Go project terminology a \"major release\" is Y.(X+1) and a minor release is Y.X.(Z+1), which is a bit unique. \r\n\r\nSo I think our policy should be:\r\n\r\nWe will apply critical security patches to the current stable release and to the most recent minor release of the previous major release - Y.(X-1).Z.",
	"user": {
		"login": "jbuberel",
		"id": 1711364,
		"type": "User",
		"site_admin": false
	},
	"created_at": "2015-09-29T21:55:00Z",
	"updated_at": "2015-09-29T21:55:00Z"
}
