{
	"id": 97632653,
	"body": "I've tried to understand what the stock `unzip` application does but I'm not that proficient with `C` code. The source is available at `ftp.info-zip.org/pub/infozip/src/` and with version 6 it looks like line `857` of `process.c` is where it calculates how many extra bytes are at the front of the file.\r\n\r\nThe Java implementation also delegates to `C`, I believe that the relevant code is [here](https://github.com/srisatish/openjdk/blob/6ffc2d129dbe05c358663364e705393c2d7322a1/jdk/src/share/native/java/util/zip/zip_util.c#L503-L505). This one seems a bit easier to understand.",
	"user": {
		"login": "philwebb",
		"id": 519772,
		"type": "User",
		"site_admin": false
	},
	"created_at": "2015-04-30T01:53:19Z",
	"updated_at": "2015-04-30T01:53:19Z"
}
