{
	"id": 66094682,
	"body": "\u003ca id=\"c1\"\u003e\u003c/a\u003eComment 1:\n\n\u003cpre\u003eIf you have concrete evidence about the claim being false, please let me know. The\nreport is too vague to support changing the docs. You might also want to read\ngolang.org/s/linger.\u003c/pre\u003e\n\n\n\n_Status changed to **WaitingForReply**._",
	"user": {
		"login": "rsc",
		"id": 104030,
		"type": "User",
		"site_admin": false
	},
	"created_at": "2014-05-21T14:53:19Z",
	"updated_at": "2014-12-08T10:44:11Z"
}
