{
	"id": 164079929,
	"body": "It seems like a regularization to accept %X, but there is always a cost to any addition of a feature. Taking that worry too far, we can't change anything ever.\r\n\r\nThe problem of versioning is being addressed by the community, and in that light I think it's fine for this minor cleanup to persist.",
	"user": {
		"login": "robpike",
		"id": 4324516,
		"type": "User",
		"site_admin": false
	},
	"created_at": "2015-12-11T23:38:21Z",
	"updated_at": "2015-12-11T23:38:21Z"
}
