{
	"id": 66056729,
	"body": "\u003ca id=\"c6\"\u003e\u003c/a\u003eComment 6 by **paulo.jpinto**:\n\n\u003cpre\u003eI just moved the variable to the global scope and the panic went away. It might be the\nreal reason, as you are saying.\n\nIt'll try again later on, when I am back at home, on the full example.\u003c/pre\u003e",
	"user": {
		"login": "gopherbot",
		"id": 8566911,
		"type": "User",
		"site_admin": false
	},
	"created_at": "2011-05-31T14:09:54Z",
	"updated_at": "2014-12-08T10:10:22Z"
}
