{
	"id": 56447346,
	"number": 9768,
	"state": "closed",
	"title": "liblink, cmd/9g: [dev.cc] -S output messed up",
	"body": "Compiling even the most trivial file such as:\r\n\r\n```go\r\npackage main\r\n\r\nfunc main() {\r\n\r\n}\r\n```\r\n\r\nwith 9g -S from the dev.cc branch produces insane output (https://gist.github.com/mwhudson/747ac3935cb84080a409, scroll to the right).  What seems to be happening is that each time an instruction is printed it reprints all instructions from that function already, like some buffer isn't being reset or something.  It doesn't happen on master.",
	"user": {
		"login": "mwhudson",
		"id": 672022,
		"type": "User",
		"site_admin": false
	},
	"labels": [
		{
			"name": "FrozenDueToAge"
		}
	],
	"comments": 1,
	"closed_at": "2015-02-03T22:50:56Z",
	"created_at": "2015-02-03T22:24:01Z",
	"updated_at": "2016-06-25T01:59:59Z"
}
