{
	"id": 189977428,
	"body": "I'd love to see this fixed. Interfaces is Go are pretty awesome and this is a fly in the ointment. I wonder what the original justification was for generating errors under these conditions? As long as the overlapping method signatures are identical I can't imagine why you'd ever want the compiler to flag this as an error.",
	"user": {
		"login": "jdef",
		"id": 2348332,
		"type": "User",
		"site_admin": false
	},
	"created_at": "2016-02-29T00:14:29Z",
	"updated_at": "2016-02-29T00:14:29Z"
}
