{
	"id": 51280424,
	"number": 3330,
	"state": "closed",
	"title": "reflect.MakeSlice can make slice with cap \u003c len",
	"body": "\u003cpre\u003eBefore filing a bug, please check whether it has been fixed since\nthe latest release: run \u0026quot;hg pull\u0026quot;, \u0026quot;hg update default\u0026quot;, rebuild, and\nretry\nwhat you did to\nreproduce the problem.  Thanks.\n\nWhat steps will reproduce the problem?\n1. Run the attached code, makeslice.go\n\nWhat is the expected output?\nSensible outcomes should be either a panic or an output of \u0026quot;0 non-zero values\u0026quot;\n- the expected behaviour is not specified in the documentation.\n\nWhat do you see instead?\nlen \u0026gt; cap\n627 non-zero values\n\nWhich compiler are you using (5g, 6g, 8g, gccgo)?\n6g\n\nWhich operating system are you using?\nUbuntu lucid\n\nWhich revision are you using?  (hg identify)\n3cdba7b0650c weekly/weekly.2012-03-13\n\nPlease provide any additional information below.\u003c/pre\u003e\n\n\n\n\n\nAttachments:\n\n1. \u003ca href=\"https://storage.googleapis.com/go-attachment/3330/0/makeslice.go\"\u003emakeslice.go\u003c/a\u003e (319 bytes)",
	"user": {
		"login": "kortschak",
		"id": 275221,
		"type": "User",
		"site_admin": false
	},
	"labels": [
		{
			"name": "FrozenDueToAge"
		}
	],
	"assignee": {
		"login": "dsymonds",
		"id": 31506,
		"type": "User",
		"site_admin": false
	},
	"comments": 4,
	"closed_at": "2014-12-08T10:17:17Z",
	"created_at": "2012-03-16T06:05:37Z",
	"updated_at": "2016-06-24T22:15:37Z",
	"milestone": {
		"id": 1061233,
		"number": 7,
		"title": "Go1"
	}
}
