{
	"id": 66077698,
	"body": "\u003ca id=\"c24\"\u003e\u003c/a\u003eComment 24:\n\n\u003cpre\u003eRe #23: Right, I'm aware the change is a single const value and it is easy to do (I\ncompile Go from source anyway) but I don't see a benefit in Windows having that large of\narena to begin with as Windows maxes out at 4 TB anyway. And it evidently has\nsignificant cost to use the current mechanism on that OS.\u003c/pre\u003e",
	"user": {
		"login": "kardianos",
		"id": 755121,
		"type": "User",
		"site_admin": false
	},
	"created_at": "2013-05-06T21:37:46Z",
	"updated_at": "2014-12-08T10:28:11Z"
}
