{
	"id": 91713948,
	"body": "If the external linking change fixes the problem then it's great.\r\nHowever, if it's not, there are possibilities that the usage of\r\nlongjmp is just incompatible with cgo.\r\n\r\nWithout looking at the source code, I can't be sure whether the\r\nlongjmp usage is inherently incompatible with cgo.\r\n\r\nOn the plus side, as Lua's longjmp based error handling is portable,\r\nif the problem doesn't exist on Linux, then I think the longjmp usage\r\nshould be fine and the external linking work should fix the windows\r\nissue.\r\n\r\nPlease try again with the current tip. Thanks.\r\n(the external linking code went in on Mar 23.)",
	"user": {
		"login": "minux",
		"id": 135652,
		"type": "User",
		"site_admin": false
	},
	"created_at": "2015-04-10T23:16:10Z",
	"updated_at": "2015-04-10T23:16:10Z"
}
