{
	"id": 66098356,
	"body": "\u003ca id=\"c6\"\u003e\u003c/a\u003eComment 6:\n\n\u003cpre\u003ei'm not against this idea, but previous experiences\nshowed that qemu-system doesn't do well at exciting\nconcurrent code paths, so we will still need real\nhardware to catch, e.g., sync/atomic and runtime\nproblems.\u003c/pre\u003e",
	"user": {
		"login": "minux",
		"id": 135652,
		"type": "User",
		"site_admin": false
	},
	"created_at": "2014-09-04T17:06:25Z",
	"updated_at": "2014-12-08T10:47:59Z"
}
