{
	"id": 66089568,
	"body": "\u003ca id=\"c3\"\u003e\u003c/a\u003eComment 3 by **kell.sommers**:\n\n\u003cpre\u003eI disabled Power Nap feature and didn't see any changes. As far as I know Power Nap\nallows applications like email to periodically check email. It's not clear to me how\nthis affects performance when the machine isn't sleeping.\n\nAlso sorry for being vague on some of the details. The Mac I am testing on is already\nrunning 10.9.1.\u003c/pre\u003e",
	"user": {
		"login": "gopherbot",
		"id": 8566911,
		"type": "User",
		"site_admin": false
	},
	"created_at": "2013-12-22T02:25:38Z",
	"updated_at": "2014-12-08T10:39:00Z"
}
