{
	"id": 51277866,
	"number": 1484,
	"state": "closed",
	"title": "rpc: error causes phase mismatch",
	"body": "\u003cpre\u003eIf the rpc package cannot find the requested method, it does not read\nthe body of the method request, meaning that the next request\nreads the body instead of the header.\n\n6g darwin 76543d680825+ tip\u003c/pre\u003e\n\n\n\n\n\nAttachments:\n\n1. \u003ca href=\"https://storage.googleapis.com/go-attachment/1484/0/tst.go\"\u003etst.go\u003c/a\u003e (502 bytes)",
	"user": {
		"login": "rogpeppe",
		"id": 66491,
		"type": "User",
		"site_admin": false
	},
	"labels": [
		{
			"name": "FrozenDueToAge"
		}
	],
	"assignee": {
		"login": "rsc",
		"id": 104030,
		"type": "User",
		"site_admin": false
	},
	"comments": 10,
	"closed_at": "2014-12-08T10:08:32Z",
	"created_at": "2011-02-07T15:09:01Z",
	"updated_at": "2016-06-24T19:24:56Z"
}
