{
	"id": 66055866,
	"body": "\u003ca id=\"c2\"\u003e\u003c/a\u003eComment 2:\n\n\u003cpre\u003ethe mime/multipart side:\n\u003ca href=\"http://code.google.com/p/go/source/detail?r=638ecff87cc688afb3546d6937cc7606f5479dc2\"\u003ehttp://code.google.com/p/go/source/detail?r=638ecff87cc688afb3546d6937cc7606f5479dc2\u003c/a\u003e\n\nthe http side: \n\u003ca href=\"http://code.google.com/p/go/source/detail?r=4449389b968ec82b0e9b7382d27ebb333c22f4d0\"\u003ehttp://code.google.com/p/go/source/detail?r=4449389b968ec82b0e9b7382d27ebb333c22f4d0\u003c/a\u003e\u003c/pre\u003e\n\n\n\n_Status changed to **Fixed**._",
	"user": {
		"login": "bradfitz",
		"id": 2621,
		"type": "User",
		"site_admin": false
	},
	"created_at": "2011-04-28T18:29:17Z",
	"updated_at": "2014-12-08T10:09:42Z"
}
