{
	"id": 215411915,
	"body": "type HTTP struct {\r\n\tJobID           string\r\n\tJobUserID       string\r\n\tJobName         string\r\n\tJobInterval\t\tuint8\r\n\tRequestAddress  string\r\n\tRequestMethod   uint8\r\n\tRequestVersion  uint8\r\n\tRequestPort     uint32\r\n\tRequestHeader   []HTTPHeader\r\n\tRequestBody\t\tstring\r\n\tRequestUsername string\r\n\tRequestPassword string\r\n\tRequestTimeout  uint8\r\n\tResponseBody    string\r\n\tResponseContain bool\r\n}",
	"user": {
		"login": "andymacau853",
		"id": 1874941,
		"type": "User",
		"site_admin": false
	},
	"created_at": "2016-04-28T12:44:41Z",
	"updated_at": "2016-04-28T12:44:41Z"
}
