{
	"id": 66054014,
	"body": "\u003ca id=\"c2\"\u003e\u003c/a\u003eComment 2 by **graycardinalster**:\n\n\u003cpre\u003e6g -o bug1.6 bug1.go\non linux work fine\n\n8g -o bug1.8 bug1.go\n buf.Size undefined (type syscall.Stat_t has no field or method Size)\u003c/pre\u003e\n\n\n\n\n\nAttachments:\n\n1. \u003ca href=\"https://storage.googleapis.com/go-attachment/1405/2/bug1.go\"\u003ebug1.go\u003c/a\u003e (160 bytes)",
	"user": {
		"login": "gopherbot",
		"id": 8566911,
		"type": "User",
		"site_admin": false
	},
	"created_at": "2011-01-10T09:59:09Z",
	"updated_at": "2014-12-08T10:08:11Z"
}
