{
	"id": 51283751,
	"number": 5518,
	"state": "closed",
	"title": "runtime: line numbers reported by caller and callers doen't match",
	"body": "\u003cpre\u003eWhat steps will reproduce the problem?\n\n1. \u003ca href=\"http://play.golang.org/p/zd59eWdmqw\"\u003ehttp://play.golang.org/p/zd59eWdmqw\u003c/a\u003e\n2. The first and second line report different line numbers (off by 1) by they should be\nthe same\n3. The other line numbers also seem not 100% correct.\u003c/pre\u003e",
	"user": {
		"login": "griesemer",
		"id": 8528975,
		"type": "User",
		"site_admin": false
	},
	"labels": [
		{
			"name": "FrozenDueToAge"
		}
	],
	"comments": 2,
	"closed_at": "2014-12-08T10:29:57Z",
	"created_at": "2013-05-20T17:54:54Z",
	"updated_at": "2016-06-24T22:40:38Z",
	"milestone": {
		"id": 1067207,
		"number": 14,
		"title": "Go1.2"
	}
}
