{
	"id": 156943513,
	"body": "Hi,\r\n\r\nI got above issue resolved, the issue was because of old gradle. I update the gradle to 2.4(from 1.12).\r\nafter this, issue is something else.\r\n\r\n\u003e No such property: GO for class: org.golang.mobile.GobindExtension_Decorated\r\n  Possible solutions: pkg\r\n\r\nPlease help me to resolve this issue.\r\n",
	"user": {
		"login": "GhongadiAdinath",
		"id": 15847179,
		"type": "User",
		"site_admin": false
	},
	"created_at": "2015-11-16T07:10:40Z",
	"updated_at": "2015-11-16T07:10:40Z"
}
