{
	"id": 72610351,
	"body": "Same bug here:\r\nhttps://github.com/golang/sys/blob/master/windows/exec_windows.go\r\n\r\nConsider another thread calling SetCurrentDirectory.\r\nAgain the correct code requires a loop.\r\n\r\n - Jay\r\n\r\nOn Feb 3, 2015, at 12:07 AM, Jay \u003cjay.krell@cornell.edu\u003e wrote:\r\n\r\n\u003e Consider another thread calling SetEnvironmentVariable concurrently with this code.\r\n\u003e \r\n\u003e  - Jay\r\n\u003e \r\n\u003e On Feb 2, 2015, at 10:43 PM, alexbrainman \u003cnotifications@github.com\u003e wrote:\r\n\u003e \r\n\u003e\u003e Can you demonstrate the bug with a bit of code? I really don't see what the problem is. Thank you.\r\n\u003e\u003e \r\n\u003e\u003e Alex\r\n\u003e\u003e \r\n\u003e\u003e —\r\n\u003e\u003e Reply to this email directly or view it on GitHub.\r\n\u003e\u003e ",
	"user": {
		"login": "jaykrell",
		"id": 1635728,
		"type": "User",
		"site_admin": false
	},
	"created_at": "2015-02-03T08:12:48Z",
	"updated_at": "2015-02-03T08:12:48Z"
}
